polygon_crop/__init__.py
polygon_crop/img_crop.py
polygon_crop-0.0.2.dist-info/LICENSE
polygon_crop-0.0.2.dist-info/METADATA
polygon_crop-0.0.2.dist-info/WHEEL
polygon_crop-0.0.2.dist-info/top_level.txt
polygon_crop-0.0.2.dist-info/RECORD
